{
  "decks": {
    "순수": {
      "personality": "Naive",
      "overview": "탱커/서폿의 시너지가 좋아 저점이 높다. 다만 순수덱을 위해선 비비와 란이 필수.",
      "difficulty": "easy",
      "pros": [
        "유지력이 좋아 침략에서 안정적",
        "뉴비가 덱을 맞추기 쉬움 (가성비 가능)",
        "저점이 높음"
      ],
      "cons": ["PVP 상성 차이가 심함", "고점이 낮음", "보호막 원툴 (PVP에서 취약)"],
      "pve": {
        "alternatives": [
          {
            "replace": "라이카",
            "with": ["캐시", "다야"],
            "condition": "라이카 어사이드 없거나 비비 1탱으로 충분한 경우",
            "tradeoff": "성능은 캐시가 더 좋음"
          },
          {
            "replace": "우로스",
            "with": ["헤일리", "가비아"],
            "condition": "우로스 미보유 시",
            "tradeoff": "딜링 및 디버프은 헤일리, 유지력은 가비아"
          },
          {
            "replace": "란",
            "with": ["아일라", "가비아"],
            "condition": "유지력 부족시",
            "tradeoff": ""
          }
        ],
        "tips": [
          "비비 1탱으로도 충분한 경우 많음",
          "라이카 어사이드 권장",
          "뮤트는 보스전(대충돌, 프론티어)에서 활약"
        ]
      },
      "pvp": {
        "alternatives": [
          {
            "replace": "캐시",
            "with": ["에르핀", "라이카"],
            "condition": "캐시가 없을 경우 에르핀 혹은 라이카 대체",
            "tradeoff": "라이카는 어사이드 필요"
          },
          {
            "replace": "우로스",
            "with": ["헤일리", "다야"],
            "condition": "우로스/마요(멋짐) 없을 경우",
            "tradeoff": "헤일리 추천 (딜 위주)"
          },
          {
            "replace": "아일라",
            "with": ["나이아", "오팔", "라이카"],
            "condition": "유지력 보완",
            "tradeoff": "유지력은 나이아, 오팔은 서브딜+보호막"
          }
        ],
        "tips": [
          "비비 1탱으로 못 버틸 시 2탱 고려",
          "현재 줘팸에서 광기 상대로 투력 1500만 차이도 운 나쁘면 짐",
          "보호막이 장점이자 단점 즉, PVP 보호막 파괴 주의",
          "PVP : 캬롯, 가비아, 셰럼 기용 가능"
        ]
      }
    },

    "냉정": {
      "personality": "Cool",
      "overview": "광역기와 한방딜이 강한 사도가 많음. 다만 힐러가 부실",
      "difficulty": "medium",
      "pros": [
        "광역기, 한방딜이 강한 사도가 많음",
        "사도들이 어사이드만 갖추면 좋음",
        "유연한 조합"
      ],
      "cons": ["힐러 부실로 인한 낮은 유지력", "뉴비가 쓰기 어려움", "디아나(왕년) 필수"],
      "pve": {
        "alternatives": [
          {
            "replace": "이드",
            "with": ["코미(수영복)", "리코타"],
            "condition": "힐 부족 시",
            "tradeoff": "어사이드 필수"
          },
          {
            "replace": "피코라",
            "with": ["리코타"],
            "condition": "더 강한 힐 필요 시",
            "tradeoff": "어사이드 A2 필요"
          },
          {
            "replace": "우로스",
            "with": ["리코타", "아멜리아"],
            "condition": "우로스 미보유 시",
            "tradeoff": "리코타 어사이드 필수"
          }
        ],
        "tips": [
          "디아나(왕년)은 용병으로 강력 추천",
          "에스피, 리코타 사용시 어사이드 필수",
          "광역기, 한방딜이 높은 계수의 사도 많음",
          "이외에는 에스피(A2), 엘레나, 실라, 제이드(A2), 베니(베니) 사용"
        ]
      },
      "pvp": {
        "alternatives": [
          {
            "replace": "이드",
            "with": ["리코타", "바롱"],
            "condition": "이드 없을 시",
            "tradeoff": ""
          },
          {
            "replace": "바롱",
            "with": ["코미(수영복)", "피코라"],
            "condition": "유지력 부족 시",
            "tradeoff": "코미(수영복)은 어사이드 필요"
          },
          {
            "replace": "바롱",
            "with": ["우로스"],
            "condition": "유지력 부족 시",
            "tradeoff": "우로스는 공격력 증가 (35%)"
          }
        ],
        "tips": [
          "디아나(왕년) 뒤에 시저를 놓는 조합이 좋음",
          "이외에는 엘레나, 실라, 에스피(A2), 벨벳(A2), 베니(베니) 사용"
        ]
      }
    },

    "광기": {
      "personality": "Mad",
      "overview": "버프가 많고 스킬이 강력. 사도 간 시너지는 약하지만, 개별 사도 성능이 뛰어남.",
      "difficulty": "medium",
      "pros": [
        "버프를 주는 사도가 많음",
        "대부분 사도들이 크게 단점이 없음 (유연한 조합 가능)",
        "스킬이 강력함",
        "2주년 기준 활발과 함께 가장 좋은 성격"
      ],
      "cons": ["뉴비에겐 리뉴아 없으면 많이 약함", "서로 간 시너지가 잘 안 맞음"],
      "pve": {
        "alternatives": [
          {
            "replace": "네티",
            "with": ["클로에", "네르"],
            "condition": "네티가 없거나 상황을 봐서",
            "tradeoff": "네르는 매운맛/핵불맛/보스전에서 3탱 옵션으로 사용됨"
          },
          {
            "replace": "폴랑",
            "with": ["디아나"],
            "condition": "힐 부족 시",
            "tradeoff": "폴랑 어사이드가 없을 경우"
          },
          {
            "replace": ["티그(영웅) 혹은 우로스"],
            "with": ["림(혼돈)", "롤렛"],
            "condition": "후열 딜러",
            "tradeoff": "육성비용 높은 엘다인 대체"
          },
          {
            "replace": "림(혼돈)",
            "with": ["시스트", "앨리스"],
            "condition": "폴랑 어사A2 없을 시",
            "tradeoff": "롤렛도 좋지만 어사A2 권장"
          },
          {
            "replace": "네티/네르/클로에",
            "with": ["마에스트로2호"],
            "condition": "탱커 없을 시",
            "tradeoff": "티그(영웅)을 전열로도 사용 가능"
          }
        ],
        "tips": [
          "클로에, 리뉴아, 티그(영웅) 필수",
          "네르는 매운맛/핵불맛 스테이지에서 3탱으로 사용",
          "리뉴아, 티그(영웅)의 육성은 강력 추천 (용병)",
          "모자란 구석이 딱히 없음"
        ]
      },
      "pvp": {
        "alternatives": [
          {
            "replace": "롤렛",
            "with": ["우로스", "림(혼돈)"],
            "condition": "롤렛 어사이드 없을 시",
            "tradeoff": "딜은 림(혼돈)이 더 좋음"
          },
          {
            "replace": "폴랑/네티/클로에",
            "with": ["디아나", "네르"],
            "condition": "",
            "tradeoff": ""
          },
          {
            "replace": "우로스 혹은 림(혼돈)",
            "with": ["아네트", "하이디"],
            "condition": "상황을 보고 기용",
            "tradeoff": ""
          }
        ],
        "tips": [
          "림(혼돈)이 줘팸에서 높은 계수로 딜러를 자르는 역할로 기용됨",
          "이외에는 셰이디(어그로), 마에2호, 리츠, 앨리스 기용 가능"
        ]
      }
    },

    "활발": {
      "personality": "Jolly",
      "overview": "프론티어와 대충돌에 강력하며, PVE/PVP 모두 우수. 메타를 잘 타지 않아 고정적이고 안정적.",
      "difficulty": "hard",
      "pros": [
        "프론티어/대충돌에 강력한 사도가 많음",
        "PVE, PVP 두곳 다 강력",
        "메타를 잘 타지 않음 (고정적이고 안정적)",
        "유일하게 6속성 시너지 유지하며 용병 사용 가능"
      ],
      "cons": ["사도 육성 비용이 높음"],
      "pve": {
        "alternatives": [
          {
            "replace": "슈로 혹은 벨라",
            "with": ["미로"],
            "condition": "",
            "tradeoff": ""
          },
          {
            "replace": "에피카",
            "with": ["리뉴아"],
            "condition": "우이 어사이드 있을 시",
            "tradeoff": "딜 성능"
          },
          {
            "replace": "우로스 혹은 에피카(A2)",
            "with": ["슈팡"],
            "condition": "",
            "tradeoff": ""
          }
        ],
        "tips": [
          "벨라, 슈로, 우이, 에피카(어사) 필수",
          "우이의 어사이드가 있을 경우 에피카빼고 리뉴아 사용 추천",
          "이외에는 마카샤, 셀리네 기용",
          "PVE는 모모가 좋음"
        ]
      },
      "pvp": {
        "alternatives": [
          {
            "replace": "아르코",
            "with": ["에피카", "모모"],
            "condition": "아르코 미보유 시",
            "tradeoff": ""
          },
          {
            "replace": "우로스",
            "with": ["모모", "에피카"],
            "condition": "",
            "tradeoff": ""
          }
        ],
        "tips": [
          "벨라, 슈로, 우이, 에피카(어사) 필수",
          "우이의 어사이드가 있을 경우 우로스 빼고 리뉴아 사용 가능",
          "PVP는 슈팡이 더 좋음"
        ]
      }
    },

    "우울": {
      "personality": "Gloomy",
      "overview": "단일 딜링과 후열 파괴력이 뛰어남. 하지만 저점이 매우 낮고 대부분 어사이드 필수.",
      "difficulty": "hard",
      "pros": ["단일 딜링이 뛰어남", "후열 파괴력이 뛰어남"],
      "cons": [
        "저점이 상상 이상으로 매우 낮음",
        "대부분의 사도가 어사이드 필수",
        "고점이 아닐시 처참한 성능",
        "사도 육성 비용이 높음"
      ],
      "pve": {
        "alternatives": [
          {
            "replace": "우로스",
            "with": ["블랑셰"],
            "condition": "우로스 미보유 시",
            "tradeoff": ""
          },
          {
            "replace": "블랑셰",
            "with": ["샤샤", "로네(시장)"],
            "condition": "블랑셰 미보유 시",
            "tradeoff": ""
          },
          {
            "replace": "키디언",
            "with": ["리온", "림"],
            "condition": "키디언 자주 죽거나 스노키 어사이드 없을 경우",
            "tradeoff": ""
          }
        ],
        "tips": ["스노키(어사) 필수", "블랑셰 빼고 리온, 스노키, 키디언으로 3탱 운용 가능"]
      },
      "pvp": {
        "alternatives": [
          {
            "replace": "오르",
            "with": ["포셔", "힐데"],
            "condition": "오르 미보유 시",
            "tradeoff": "포셔 추천"
          },
          {
            "replace": "로네(시장)",
            "with": ["시온"],
            "condition": "",
            "tradeoff": "우로스 어사이드 없을 때도 시온 가능"
          },
          {
            "replace": "아사나",
            "with": ["리온", "키디언"],
            "condition": "아사나 미보유 시",
            "tradeoff": ""
          },
          {
            "replace": "스노키(A2)",
            "with": ["림(A2)", "코미"],
            "condition": "스노키 어사이드 없을 경우",
            "tradeoff": ""
          }
        ],
        "tips": [
          "죠안, 스노키(A2) 필수",
          "PVP는 사람마다 덱이 다름",
          "아사나, 로네(시장), 우로스랑 같이 쓰면 딜뻥이 되므로 조합이 좋음",
          "이외에는 리스티 기용"
        ]
      }
    }
  }
}
